{"base_info": {"title": "The Groundskeepers llc", "rating": 5.0, "rating_user_count": 4}, "full_info": {"address": "4985 Poor Mountain Rd, Salem, VA 24153, \u0421\u043e\u0435\u0434\u0438\u043d\u0435\u043d\u043d\u044b\u0435 \u0428\u0442\u0430\u0442\u044b", "site": "thegroundskeepersllc.com", "phone_number": "+1 540-915-7877", "plus_code": "7V57+6G \u0421\u0435\u0439\u043b\u0435\u043c, \u0412\u0438\u0440\u0434\u0436\u0438\u043d\u0438\u044f, \u0421\u0428\u0410", "timetable": ""}, "coordinate": "<iframe src=\"https://www.google.com/maps/embed?pb=!1m18!1m12!1m3!1d3175.5622891381317!2d-80.1362293!3d37.2580914!2m3!1f0!2f0!3f0!3m2!1i1024!2i768!4f13.1!3m3!1m2!1s0x0%3A0xb0d78a63df648133!2sThe%20Groundskeepers%20llc!5e0!3m2!1sru!2skz!4v1652424848934!5m2!1sru!2skz\" width=\"600\" height=\"450\" style=\"border:0;\" allowfullscreen=\"\" loading=\"lazy\" referrerpolicy=\"no-referrer-when-downgrade\"></iframe>", "base_photo": "https://streetviewpixels-pa.googleapis.com/v1/thumbnail?panoid=Wlb6WVaS2dJgL_aU8DQ9lQ&cb_client=search.gws-prod.gps&w=408&h=240&yaw=258.88675&pitch=0&thumbfov=100", "reviews": [], "photos": []}