{"base_info": {"title": "Jimmy Ball Roofing (aka\u2026jb roofing)", "rating": 4.3, "rating_user_count": 12}, "full_info": {"address": "29259 Hillman Hwy, Meadowview, VA 24361, \u0421\u043e\u0435\u0434\u0438\u043d\u0435\u043d\u043d\u044b\u0435 \u0428\u0442\u0430\u0442\u044b", "site": "jimmyballroofing.com", "phone_number": "+1 276-944-4434", "plus_code": "Q47V+8W \u041c\u0435\u0434\u043e\u0443\u0432\u044c\u044e, \u0412\u0438\u0440\u0434\u0436\u0438\u043d\u0438\u044f, \u0421\u0428\u0410", "timetable": " <tbody><tr jstcache=\"182\" jsinstance=\"0\" class=\"y0skZc\"> <td jstcache=\"183\" class=\"ylH6lf fontTitleSmall\" jsan=\"7.ylH6lf,7.fontTitleSmall\"> <div jstcache=\"184\">\u043f\u043e\u043d\u0435\u0434\u0435\u043b\u044c\u043d\u0438\u043a</div> <div jstcache=\"185\" class=\"GfF3rf\" style=\"display:none\" jsan=\"7.GfF3rf\"></div> </td> <td aria-label=\"07:30\u201319:30\" role=\"text\" jstcache=\"186\" class=\"mxowUb\"> <ul jstcache=\"187\" class=\"fontTitleSmall\" jsan=\"7.fontTitleSmall\"><li jstcache=\"188\" jsinstance=\"*0\" class=\"G8aQO\" jsan=\"7.G8aQO\">07:30\u201319:30</li></ul> <div jstcache=\"189\" class=\"GfF3rf\" style=\"display:none\"> <span jstcache=\"190\" class=\"rYsDIf\" style=\"display:none\">\u0427\u0430\u0441\u044b \u0440\u0430\u0431\u043e\u0442\u044b \u0432 \u043f\u0440\u0430\u0437\u0434\u043d\u0438\u0447\u043d\u044b\u0439 \u0434\u0435\u043d\u044c</span> <span jstcache=\"191\" class=\"zdqHHd\" style=\"display:none\">\u0427\u0430\u0441\u044b \u0440\u0430\u0431\u043e\u0442\u044b \u043c\u043e\u0433\u0443\u0442 \u043c\u0435\u043d\u044f\u0442\u044c\u0441\u044f</span> </div> </td> <td jstcache=\"192\" class=\"HuudEc\" jsan=\"7.HuudEc,t-e_-rMwTIYXc\"> <button data-hide-tooltip-on-mouse-move=\"true\" data-value=\"\u043f\u043e\u043d\u0435\u0434\u0435\u043b\u044c\u043d\u0438\u043a,07:30\u201319:30\" jsaction=\"pane.openhours.113.copy;;focus:pane.focusTooltip;blur:pane.blurTooltip\" data-tooltip=\"\u0421\u043a\u043e\u043f\u0438\u0440\u043e\u0432\u0430\u0442\u044c \u0447\u0430\u0441\u044b \u0440\u0430\u0431\u043e\u0442\u044b\" aria-label=\"\u043f\u043e\u043d\u0435\u0434\u0435\u043b\u044c\u043d\u0438\u043a,07:30\u201319:30,\u0421\u043a\u043e\u043f\u0438\u0440\u043e\u0432\u0430\u0442\u044c \u0447\u0430\u0441\u044b \u0440\u0430\u0431\u043e\u0442\u044b\" jstcache=\"196\" class=\"mWUh3d\"> <div class=\"GYnni\"></div> </button> </td> </tr><tr jstcache=\"182\" jsinstance=\"1\" class=\"y0skZc\"> <td jstcache=\"183\" class=\"ylH6lf\" jsan=\"7.ylH6lf\"> <div jstcache=\"184\">\u0432\u0442\u043e\u0440\u043d\u0438\u043a</div> <div jstcache=\"185\" class=\"GfF3rf\" style=\"display:none\" jsan=\"7.GfF3rf\"></div> </td> <td aria-label=\"07:30\u201319:30\" role=\"text\" jstcache=\"186\" class=\"mxowUb\"> <ul jstcache=\"187\"><li jstcache=\"188\" jsinstance=\"*0\" class=\"G8aQO\" jsan=\"7.G8aQO\">07:30\u201319:30</li></ul> <div jstcache=\"189\" class=\"GfF3rf\" style=\"display:none\"> <span jstcache=\"190\" class=\"rYsDIf\" style=\"display:none\">\u0427\u0430\u0441\u044b \u0440\u0430\u0431\u043e\u0442\u044b \u0432 \u043f\u0440\u0430\u0437\u0434\u043d\u0438\u0447\u043d\u044b\u0439 \u0434\u0435\u043d\u044c</span> <span jstcache=\"191\" class=\"zdqHHd\" style=\"display:none\">\u0427\u0430\u0441\u044b \u0440\u0430\u0431\u043e\u0442\u044b \u043c\u043e\u0433\u0443\u0442 \u043c\u0435\u043d\u044f\u0442\u044c\u0441\u044f</span> </div> </td> <td jstcache=\"192\" class=\"HuudEc\" jsan=\"7.HuudEc,t-e_-rMwTIYXc\"> <button data-hide-tooltip-on-mouse-move=\"true\" data-value=\"\u0432\u0442\u043e\u0440\u043d\u0438\u043a,07:30\u201319:30\" jsaction=\"pane.openhours.113.copy;;focus:pane.focusTooltip;blur:pane.blurTooltip\" data-tooltip=\"\u0421\u043a\u043e\u043f\u0438\u0440\u043e\u0432\u0430\u0442\u044c \u0447\u0430\u0441\u044b \u0440\u0430\u0431\u043e\u0442\u044b\" aria-label=\"\u0432\u0442\u043e\u0440\u043d\u0438\u043a,07:30\u201319:30,\u0421\u043a\u043e\u043f\u0438\u0440\u043e\u0432\u0430\u0442\u044c \u0447\u0430\u0441\u044b \u0440\u0430\u0431\u043e\u0442\u044b\" jstcache=\"196\" class=\"mWUh3d\"> <div class=\"GYnni\"></div> </button> </td> </tr><tr jstcache=\"182\" jsinstance=\"2\" class=\"y0skZc\"> <td jstcache=\"183\" class=\"ylH6lf\" jsan=\"7.ylH6lf\"> <div jstcache=\"184\">\u0441\u0440\u0435\u0434\u0430</div> <div jstcache=\"185\" class=\"GfF3rf\" style=\"display:none\" jsan=\"7.GfF3rf\"></div> </td> <td aria-label=\"07:30\u201319:30\" role=\"text\" jstcache=\"186\" class=\"mxowUb\"> <ul jstcache=\"187\"><li jstcache=\"188\" jsinstance=\"*0\" class=\"G8aQO\" jsan=\"7.G8aQO\">07:30\u201319:30</li></ul> <div jstcache=\"189\" class=\"GfF3rf\" style=\"display:none\"> <span jstcache=\"190\" class=\"rYsDIf\" style=\"display:none\">\u0427\u0430\u0441\u044b \u0440\u0430\u0431\u043e\u0442\u044b \u0432 \u043f\u0440\u0430\u0437\u0434\u043d\u0438\u0447\u043d\u044b\u0439 \u0434\u0435\u043d\u044c</span> <span jstcache=\"191\" class=\"zdqHHd\" style=\"display:none\">\u0427\u0430\u0441\u044b \u0440\u0430\u0431\u043e\u0442\u044b \u043c\u043e\u0433\u0443\u0442 \u043c\u0435\u043d\u044f\u0442\u044c\u0441\u044f</span> </div> </td> <td jstcache=\"192\" class=\"HuudEc\" jsan=\"7.HuudEc,t-e_-rMwTIYXc\"> <button data-hide-tooltip-on-mouse-move=\"true\" data-value=\"\u0441\u0440\u0435\u0434\u0430,07:30\u201319:30\" jsaction=\"pane.openhours.113.copy;;focus:pane.focusTooltip;blur:pane.blurTooltip\" data-tooltip=\"\u0421\u043a\u043e\u043f\u0438\u0440\u043e\u0432\u0430\u0442\u044c \u0447\u0430\u0441\u044b \u0440\u0430\u0431\u043e\u0442\u044b\" aria-label=\"\u0441\u0440\u0435\u0434\u0430,07:30\u201319:30,\u0421\u043a\u043e\u043f\u0438\u0440\u043e\u0432\u0430\u0442\u044c \u0447\u0430\u0441\u044b \u0440\u0430\u0431\u043e\u0442\u044b\" jstcache=\"196\" class=\"mWUh3d\"> <div class=\"GYnni\"></div> </button> </td> </tr><tr jstcache=\"182\" jsinstance=\"3\" class=\"y0skZc\"> <td jstcache=\"183\" class=\"ylH6lf\" jsan=\"7.ylH6lf\"> <div jstcache=\"184\">\u0447\u0435\u0442\u0432\u0435\u0440\u0433</div> <div jstcache=\"185\" class=\"GfF3rf\" style=\"display:none\" jsan=\"7.GfF3rf\"></div> </td> <td aria-label=\"07:30\u201319:30\" role=\"text\" jstcache=\"186\" class=\"mxowUb\"> <ul jstcache=\"187\"><li jstcache=\"188\" jsinstance=\"*0\" class=\"G8aQO\" jsan=\"7.G8aQO\">07:30\u201319:30</li></ul> <div jstcache=\"189\" class=\"GfF3rf\" style=\"display:none\"> <span jstcache=\"190\" class=\"rYsDIf\" style=\"display:none\">\u0427\u0430\u0441\u044b \u0440\u0430\u0431\u043e\u0442\u044b \u0432 \u043f\u0440\u0430\u0437\u0434\u043d\u0438\u0447\u043d\u044b\u0439 \u0434\u0435\u043d\u044c</span> <span jstcache=\"191\" class=\"zdqHHd\" style=\"display:none\">\u0427\u0430\u0441\u044b \u0440\u0430\u0431\u043e\u0442\u044b \u043c\u043e\u0433\u0443\u0442 \u043c\u0435\u043d\u044f\u0442\u044c\u0441\u044f</span> </div> </td> <td jstcache=\"192\" class=\"HuudEc\" jsan=\"7.HuudEc,t-e_-rMwTIYXc\"> <button data-hide-tooltip-on-mouse-move=\"true\" data-value=\"\u0447\u0435\u0442\u0432\u0435\u0440\u0433,07:30\u201319:30\" jsaction=\"pane.openhours.113.copy;;focus:pane.focusTooltip;blur:pane.blurTooltip\" data-tooltip=\"\u0421\u043a\u043e\u043f\u0438\u0440\u043e\u0432\u0430\u0442\u044c \u0447\u0430\u0441\u044b \u0440\u0430\u0431\u043e\u0442\u044b\" aria-label=\"\u0447\u0435\u0442\u0432\u0435\u0440\u0433,07:30\u201319:30,\u0421\u043a\u043e\u043f\u0438\u0440\u043e\u0432\u0430\u0442\u044c \u0447\u0430\u0441\u044b \u0440\u0430\u0431\u043e\u0442\u044b\" jstcache=\"196\" class=\"mWUh3d\"> <div class=\"GYnni\"></div> </button> </td> </tr><tr jstcache=\"182\" jsinstance=\"4\" class=\"y0skZc\"> <td jstcache=\"183\" class=\"ylH6lf\" jsan=\"7.ylH6lf\"> <div jstcache=\"184\">\u043f\u044f\u0442\u043d\u0438\u0446\u0430</div> <div jstcache=\"185\" class=\"GfF3rf\" style=\"display:none\" jsan=\"7.GfF3rf\"></div> </td> <td aria-label=\"07:30\u201319:30\" role=\"text\" jstcache=\"186\" class=\"mxowUb\"> <ul jstcache=\"187\"><li jstcache=\"188\" jsinstance=\"*0\" class=\"G8aQO\" jsan=\"7.G8aQO\">07:30\u201319:30</li></ul> <div jstcache=\"189\" class=\"GfF3rf\" style=\"display:none\"> <span jstcache=\"190\" class=\"rYsDIf\" style=\"display:none\">\u0427\u0430\u0441\u044b \u0440\u0430\u0431\u043e\u0442\u044b \u0432 \u043f\u0440\u0430\u0437\u0434\u043d\u0438\u0447\u043d\u044b\u0439 \u0434\u0435\u043d\u044c</span> <span jstcache=\"191\" class=\"zdqHHd\" style=\"display:none\">\u0427\u0430\u0441\u044b \u0440\u0430\u0431\u043e\u0442\u044b \u043c\u043e\u0433\u0443\u0442 \u043c\u0435\u043d\u044f\u0442\u044c\u0441\u044f</span> </div> </td> <td jstcache=\"192\" class=\"HuudEc\" jsan=\"7.HuudEc,t-e_-rMwTIYXc\"> <button data-hide-tooltip-on-mouse-move=\"true\" data-value=\"\u043f\u044f\u0442\u043d\u0438\u0446\u0430,07:30\u201319:30\" jsaction=\"pane.openhours.113.copy;;focus:pane.focusTooltip;blur:pane.blurTooltip\" data-tooltip=\"\u0421\u043a\u043e\u043f\u0438\u0440\u043e\u0432\u0430\u0442\u044c \u0447\u0430\u0441\u044b \u0440\u0430\u0431\u043e\u0442\u044b\" aria-label=\"\u043f\u044f\u0442\u043d\u0438\u0446\u0430,07:30\u201319:30,\u0421\u043a\u043e\u043f\u0438\u0440\u043e\u0432\u0430\u0442\u044c \u0447\u0430\u0441\u044b \u0440\u0430\u0431\u043e\u0442\u044b\" jstcache=\"196\" class=\"mWUh3d\"> <div class=\"GYnni\"></div> </button> </td> </tr><tr jstcache=\"182\" jsinstance=\"5\" class=\"y0skZc\"> <td jstcache=\"183\" class=\"ylH6lf\" jsan=\"7.ylH6lf\"> <div jstcache=\"184\">\u0441\u0443\u0431\u0431\u043e\u0442\u0430</div> <div jstcache=\"185\" class=\"GfF3rf\" style=\"display:none\" jsan=\"7.GfF3rf\"></div> </td> <td aria-label=\"07:30\u201319:30\" role=\"text\" jstcache=\"186\" class=\"mxowUb\"> <ul jstcache=\"187\"><li jstcache=\"188\" jsinstance=\"*0\" class=\"G8aQO\" jsan=\"7.G8aQO\">07:30\u201319:30</li></ul> <div jstcache=\"189\" class=\"GfF3rf\" style=\"display:none\"> <span jstcache=\"190\" class=\"rYsDIf\" style=\"display:none\">\u0427\u0430\u0441\u044b \u0440\u0430\u0431\u043e\u0442\u044b \u0432 \u043f\u0440\u0430\u0437\u0434\u043d\u0438\u0447\u043d\u044b\u0439 \u0434\u0435\u043d\u044c</span> <span jstcache=\"191\" class=\"zdqHHd\" style=\"display:none\">\u0427\u0430\u0441\u044b \u0440\u0430\u0431\u043e\u0442\u044b \u043c\u043e\u0433\u0443\u0442 \u043c\u0435\u043d\u044f\u0442\u044c\u0441\u044f</span> </div> </td> <td jstcache=\"192\" class=\"HuudEc\" jsan=\"7.HuudEc,t-e_-rMwTIYXc\"> <button data-hide-tooltip-on-mouse-move=\"true\" data-value=\"\u0441\u0443\u0431\u0431\u043e\u0442\u0430,07:30\u201319:30\" jsaction=\"pane.openhours.113.copy;;focus:pane.focusTooltip;blur:pane.blurTooltip\" data-tooltip=\"\u0421\u043a\u043e\u043f\u0438\u0440\u043e\u0432\u0430\u0442\u044c \u0447\u0430\u0441\u044b \u0440\u0430\u0431\u043e\u0442\u044b\" aria-label=\"\u0441\u0443\u0431\u0431\u043e\u0442\u0430,07:30\u201319:30,\u0421\u043a\u043e\u043f\u0438\u0440\u043e\u0432\u0430\u0442\u044c \u0447\u0430\u0441\u044b \u0440\u0430\u0431\u043e\u0442\u044b\" jstcache=\"196\" class=\"mWUh3d\"> <div class=\"GYnni\"></div> </button> </td> </tr><tr jstcache=\"182\" jsinstance=\"*6\" class=\"y0skZc\"> <td jstcache=\"183\" class=\"ylH6lf\" jsan=\"7.ylH6lf\"> <div jstcache=\"184\">\u0432\u043e\u0441\u043a\u0440\u0435\u0441\u0435\u043d\u044c\u0435</div> <div jstcache=\"185\" class=\"GfF3rf\" style=\"display:none\" jsan=\"7.GfF3rf\"></div> </td> <td aria-label=\"\u0417\u0430\u043a\u0440\u044b\u0442\u043e\" role=\"text\" jstcache=\"186\" class=\"mxowUb\"> <ul jstcache=\"187\"><li jstcache=\"188\" jsinstance=\"*0\" class=\"G8aQO\" jsan=\"7.G8aQO\">\u0417\u0430\u043a\u0440\u044b\u0442\u043e</li></ul> <div jstcache=\"189\" class=\"GfF3rf\" style=\"display:none\"> <span jstcache=\"190\" class=\"rYsDIf\" style=\"display:none\">\u0427\u0430\u0441\u044b \u0440\u0430\u0431\u043e\u0442\u044b \u0432 \u043f\u0440\u0430\u0437\u0434\u043d\u0438\u0447\u043d\u044b\u0439 \u0434\u0435\u043d\u044c</span> <span jstcache=\"191\" class=\"zdqHHd\" style=\"display:none\">\u0427\u0430\u0441\u044b \u0440\u0430\u0431\u043e\u0442\u044b \u043c\u043e\u0433\u0443\u0442 \u043c\u0435\u043d\u044f\u0442\u044c\u0441\u044f</span> </div> </td> <td jstcache=\"192\" class=\"HuudEc\" jsan=\"7.HuudEc,t-e_-rMwTIYXc\"> <button data-hide-tooltip-on-mouse-move=\"true\" data-value=\"\u0432\u043e\u0441\u043a\u0440\u0435\u0441\u0435\u043d\u044c\u0435,\u0417\u0430\u043a\u0440\u044b\u0442\u043e\" jsaction=\"pane.openhours.113.copy;;focus:pane.focusTooltip;blur:pane.blurTooltip\" data-tooltip=\"\u0421\u043a\u043e\u043f\u0438\u0440\u043e\u0432\u0430\u0442\u044c \u0447\u0430\u0441\u044b \u0440\u0430\u0431\u043e\u0442\u044b\" aria-label=\"\u0432\u043e\u0441\u043a\u0440\u0435\u0441\u0435\u043d\u044c\u0435,\u0417\u0430\u043a\u0440\u044b\u0442\u043e,\u0421\u043a\u043e\u043f\u0438\u0440\u043e\u0432\u0430\u0442\u044c \u0447\u0430\u0441\u044b \u0440\u0430\u0431\u043e\u0442\u044b\" jstcache=\"196\" class=\"mWUh3d\"> <div class=\"GYnni\"></div> </button> </td> </tr> </tbody>"}, "coordinate": "<iframe src=\"https://www.google.com/maps/embed?pb=!1m18!1m12!1m3!1d3196.3018862124804!2d-81.8551537!3d36.76332469999999!2m3!1f0!2f0!3f0!3m2!1i1024!2i768!4f13.1!3m3!1m2!1s0x0%3A0xf330b8651da9718e!2sJimmy%20Ball%20Roofing%20(aka%E2%80%A6jb%20roofing)!5e0!3m2!1sru!2skz!4v1658174752150!5m2!1sru!2skz\" width=\"600\" height=\"450\" style=\"border:0;\" allowfullscreen=\"\" loading=\"lazy\" referrerpolicy=\"no-referrer-when-downgrade\"></iframe>", "base_photo": "https://lh5.googleusercontent.com/p/AF1QipOzWEVI6au3nfXNjpO5ravJXEk98z1R7Scrr7YT", "reviews": [{"rating": 5, "text": "(\u041f\u0435\u0440\u0435\u0432\u0435\u0434\u0435\u043d\u043e Google) \u041e\u0431\u044b\u0447\u043d\u043e \u044f \u043d\u0438 \u043d\u0430 \u0447\u0442\u043e \u043d\u0435 \u043f\u0438\u0448\u0443 \u043e\u0442\u0437\u044b\u0432\u044b, \u043d\u043e \u043f\u043e\u0441\u043b\u0435 \u0442\u043e\u0439 \u043f\u043e\u0442\u0440\u044f\u0441\u0430\u044e\u0449\u0435\u0439 \u0440\u0430\u0431\u043e\u0442\u044b, \u043a\u043e\u0442\u043e\u0440\u0443\u044e \u043e\u043d\u0438 \u0434\u043b\u044f \u043c\u0435\u043d\u044f \u0441\u0434\u0435\u043b\u0430\u043b\u0438, \u044f \u0434\u043e\u043b\u0436\u0435\u043d \u0447\u0442\u043e-\u0442\u043e \u043d\u0430\u043f\u0438\u0441\u0430\u0442\u044c. \u041e\u043d\u0438 \u043e\u0442\u0432\u0435\u0442\u0438\u043b\u0438 \u043d\u0430 \u0437\u0432\u043e\u043d\u043e\u043a, \u043a\u043e\u0433\u0434\u0430 \u044f \u0432\u043f\u0435\u0440\u0432\u044b\u0435 \u043f\u043e\u0437\u0432\u043e\u043d\u0438\u043b, \u043f\u0440\u0438\u0448\u043b\u0438, \u0447\u0442\u043e\u0431\u044b \u043e\u0446\u0435\u043d\u0438\u0442\u044c \u0441\u0442\u043e\u0438\u043c\u043e\u0441\u0442\u044c \u0440\u0435\u043c\u043e\u043d\u0442\u0430 \u043a\u0440\u044b\u0448\u0438 \u0432 \u0442\u043e\u0442 \u0434\u0435\u043d\u044c, \u043a\u043e\u0433\u0434\u0430 \u043e\u0431\u0435\u0449\u0430\u043b\u0438, \u0438 \u0432\u0435\u0440\u043d\u0443\u043b\u0438\u0441\u044c \u043c\u0435\u043d\u0435\u0435 \u0447\u0435\u043c \u0447\u0435\u0440\u0435\u0437 \u0434\u0432\u0430 \u0434\u043d\u044f, \u0447\u0442\u043e\u0431\u044b \u0437\u0430\u0432\u0435\u0440\u0448\u0438\u0442\u044c \u0440\u0430\u0431\u043e\u0442\u0443, \u043a\u0430\u043a \u0438 \u043e\u0431\u0435\u0449\u0430\u043b\u0438. \u0420\u0435\u043c\u043e\u043d\u0442 \u043f\u043e\u0442\u0440\u0435\u0431\u043e\u0432\u0430\u043b \u0441\u0435\u0440\u044c\u0435\u0437\u043d\u044b\u0445 \u0442\u0440\u0443\u0434\u043e\u0437\u0430\u0442\u0440\u0430\u0442, \u043d\u043e \u0431\u044b\u043b \u0441\u0434\u0435\u043b\u0430\u043d \u0431\u044b\u0441\u0442\u0440\u043e \u0438 \u043f\u0440\u043e\u0444\u0435\u0441\u0441\u0438\u043e\u043d\u0430\u043b\u044c\u043d\u043e. \u042d\u043a\u0438\u043f\u0430\u0436 \u0443\u0431\u0438\u0440\u0430\u043b\u0441\u044f \u0442\u0430\u043a \u0445\u043e\u0440\u043e\u0448\u043e, \u0447\u0442\u043e \u044f \u0434\u0430\u0436\u0435 \u043d\u0435 \u043c\u043e\u0433 \u0441\u043a\u0430\u0437\u0430\u0442\u044c, \u0447\u0442\u043e \u043e\u043d\u0438 \u0431\u044b\u043b\u0438 \u0442\u0430\u043c. \u041e\u0447\u0435\u043d\u044c \u043f\u0440\u0438\u0435\u043c\u043b\u0435\u043c\u0430\u044f \u0446\u0435\u043d\u0430 \u0434\u043b\u044f \u043d\u0435\u043e\u0431\u0445\u043e\u0434\u0438\u043c\u043e\u0433\u043e \u043e\u0431\u044a\u0435\u043c\u0430 \u0440\u0430\u0431\u043e\u0442. \u0423 \u043c\u0435\u043d\u044f \u0431\u044b\u043b\u043e \u043c\u043d\u043e\u0433\u043e \u043f\u0440\u043e\u0431\u043b\u0435\u043c \u0441 \u0442\u0435\u043c, \u0447\u0442\u043e\u0431\u044b \u0437\u0430\u0441\u0442\u0430\u0432\u0438\u0442\u044c \u043f\u043e\u0434\u0440\u044f\u0434\u0447\u0438\u043a\u043e\u0432 \u043e\u0442\u0432\u0435\u0442\u0438\u0442\u044c \u043d\u0430 \u0442\u0435\u043b\u0435\u0444\u043e\u043d\u043d\u044b\u0439 \u0437\u0432\u043e\u043d\u043e\u043a \u0438\u043b\u0438 \u044f\u0432\u0438\u0442\u044c\u0441\u044f, \u0442\u0430\u043a \u043a\u0430\u043a \u044f \u0436\u0438\u043b \u0432 \u044d\u0442\u043e\u043c \u0440\u0430\u0439\u043e\u043d\u0435, \u043f\u043e\u044d\u0442\u043e\u043c\u0443 \u044f \u0431\u044b\u043b \u043e\u0447\u0435\u043d\u044c \u0432\u043f\u0435\u0447\u0430\u0442\u043b\u0435\u043d Jimmy Ball Roofing. \u041e\u043d\u0438 \u0441\u0442\u0430\u043d\u0443\u0442 \u043c\u043e\u0438\u043c \u043d\u043e\u0432\u044b\u043c \u043f\u043e\u043c\u043e\u0449\u043d\u0438\u043a\u043e\u043c \u043f\u0440\u0438 \u043b\u044e\u0431\u044b\u0445 \u043a\u0440\u043e\u0432\u0435\u043b\u044c\u043d\u044b\u0445 \u043d\u0443\u0436\u0434\u0430\u0445, \u0438 \u044f \u0431\u0443\u0434\u0443 \u0440\u0435\u043a\u043e\u043c\u0435\u043d\u0434\u043e\u0432\u0430\u0442\u044c \u0438\u0445 \u0432\u0441\u0435\u043c, \u043a\u043e\u0433\u043e \u0437\u043d\u0430\u044e \u0432 \u0431\u0443\u0434\u0443\u0449\u0435\u043c. \u0415\u0441\u043b\u0438 \u0431\u044b \u0432\u0441\u0435 \u043f\u043e\u0434\u0440\u044f\u0434\u0447\u0438\u043a\u0438 \u0432 \u044d\u0442\u043e\u0439 \u0441\u0444\u0435\u0440\u0435 \u0431\u044b\u043b\u0438 \u0442\u0430\u043a\u0438\u043c\u0438 \u043f\u0440\u043e\u0444\u0435\u0441\u0441\u0438\u043e\u043d\u0430\u043b\u0430\u043c\u0438!\n\n(\u041e\u0440\u0438\u0433\u0438\u043d\u0430\u043b)\nI usually don\u2019t write reviews for anything, but after the awesome work they did for me, I have to write something. They answered the phone the first time I called, showed up to give an estimate on a roof repair on the day they said they would, and were back less than two days later to complete the job as promised. The repair involved some serious labor, but was done quickly and professionally. The crew cleaned up so well, I couldn\u2019t even tell they had been there. Very reasonably priced for the amount of work that was required. I\u2019ve had a lot of trouble getting contractors to answer the phone or show up since I\u2019ve lived in this area, so I was thoroughly impressed with Jimmy Ball Roofing. They will be my new go-to for any roofing needs and I will be recommending them to everyone I know in the future. If only all contractors in this area were this professional!"}, {"rating": 5, "text": "(\u041f\u0435\u0440\u0435\u0432\u0435\u0434\u0435\u043d\u043e Google) \u041e\u0447\u0435\u043d\u044c \u0440\u0435\u043a\u043e\u043c\u0435\u043d\u0434\u0443\u044e, \u0435\u0441\u043b\u0438 \u0432\u044b \u0445\u043e\u0442\u0438\u0442\u0435, \u0447\u0442\u043e\u0431\u044b \u043d\u043e\u0432\u0443\u044e \u043a\u0440\u044b\u0448\u0443 \u0443\u0441\u0442\u0430\u043d\u0430\u0432\u043b\u0438\u0432\u0430\u043b\u0438 \u043f\u0440\u043e\u0444\u0435\u0441\u0441\u0438\u043e\u043d\u0430\u043b\u044b. \u0414\u0436\u0430\u0440\u0440\u043e\u0434 \u0438 \u0435\u0433\u043e \u043a\u043e\u043c\u0430\u043d\u0434\u0430 \u2014 \u043f\u0435\u0440\u0444\u0435\u043a\u0446\u0438\u043e\u043d\u0438\u0441\u0442\u044b, \u0438 \u0432\u044b \u043e\u043f\u0440\u0435\u0434\u0435\u043b\u0435\u043d\u043d\u043e \u043c\u043e\u0436\u0435\u0442\u0435 \u0441\u043a\u0430\u0437\u0430\u0442\u044c, \u0447\u0442\u043e \u043e\u043d\u0438 \u0433\u043e\u0440\u0434\u044f\u0442\u0441\u044f \u0441\u0432\u043e\u0435\u0439 \u0440\u0430\u0431\u043e\u0442\u043e\u0439! \u0415\u0441\u043b\u0438 \u043a\u043e\u043c\u0443-\u0442\u043e \u043d\u0443\u0436\u043d\u0430 \u043a\u0440\u044b\u0448\u0430, \u044f \u0443\u043a\u0430\u0437\u044b\u0432\u0430\u044e \u0435\u043c\u0443 \u043d\u0430\u043f\u0440\u0430\u0432\u043b\u0435\u043d\u0438\u0435. \u0412\u0430\u0448\u0438 \u0440\u0430\u0431\u043e\u0442\u044b \u0432\u0441\u0435\u0433\u0434\u0430 \u0432\u044b\u0433\u043b\u044f\u0434\u044f\u0442 \u043f\u043e\u0442\u0440\u044f\u0441\u0430\u044e\u0449\u0435!\n\n(\u041e\u0440\u0438\u0433\u0438\u043d\u0430\u043b)\nWould highly recommend if you're wanting a new roof installed by professionals. Jarrod and his crew are perfectionists and you can definitely tell they take pride in their work! If someone needs a roof, I point them in his direction. Your work always looks amazing!"}, {"rating": 5, "text": "(\u041f\u0435\u0440\u0435\u0432\u0435\u0434\u0435\u043d\u043e Google) \u0411\u043e\u043b\u044c\u0448\u043e\u0439 \u043e\u043f\u044b\u0442 \u0440\u0430\u0431\u043e\u0442\u044b \u0441 \u043d\u0438\u043c\u0438 \u0441\u0434\u0435\u043b\u0430\u043b \u043e\u0442\u043b\u0438\u0447\u043d\u0443\u044e \u0440\u0430\u0431\u043e\u0442\u0443 \u0438\u043c\u0435\u043d\u043d\u043e \u0442\u0430\u043a, \u043a\u0430\u043a \u043c\u043d\u0435 \u0441\u043a\u0430\u0437\u0430\u043b\u0438, \u0438 \u0434\u0430\u0436\u0435 \u0431\u043e\u043b\u044c\u0448\u0435 \u043f\u043e\u0445\u043e\u0434\u0438\u043b \u043d\u0430 \u043e\u0447\u0438\u0441\u0442\u043a\u0443 \u0432\u043e\u0434\u043e\u0441\u0442\u043e\u0447\u043d\u044b\u0445 \u0436\u0435\u043b\u043e\u0431\u043e\u0432 \u0438 \u043e\u0442\u0441\u0443\u0442\u0441\u0442\u0432\u0438\u0435 \u0431\u0435\u0441\u043f\u043e\u0440\u044f\u0434\u043a\u0430 \u043d\u0430 \u0440\u0430\u0431\u043e\u0447\u0435\u043c \u043c\u0435\u0441\u0442\u0435. \u041e\u043d\u0438 \u0431\u044b\u043b\u0438 \u0442\u0430\u043c \u0438 \u0441\u0434\u0435\u043b\u0430\u043b\u0438 \u0440\u0430\u0431\u043e\u0442\u0443 \u0431\u044b\u0441\u0442\u0440\u0435\u0435, \u0447\u0435\u043c \u044f \u0434\u0443\u043c\u0430\u043b. \u0417\u0430\u043c\u0435\u0447\u0430\u0442\u0435\u043b\u044c\u043d\u044b\u0435 \u043b\u044e\u0434\u0438, \u0441 \u043a\u043e\u0442\u043e\u0440\u044b\u043c\u0438 \u043f\u0440\u0438\u044f\u0442\u043d\u043e \u0440\u0430\u0431\u043e\u0442\u0430\u0442\u044c, \u0438 \u043e\u0447\u0435\u043d\u044c \u0447\u0435\u0441\u0442\u043d\u044b\u0435, \u0447\u0442\u043e \u0442\u0440\u0443\u0434\u043d\u043e \u043d\u0430\u0439\u0442\u0438 \u0432 \u043d\u0430\u0448\u0438 \u0434\u043d\u0438. \u0411\u0443\u0434\u0443 \u0438\u0441\u043f\u043e\u043b\u044c\u0437\u043e\u0432\u0430\u0442\u044c \u0438\u0445 \u0441\u043d\u043e\u0432\u0430, \u043a\u043e\u0433\u0434\u0430 \u043c\u043d\u0435 \u043d\u0443\u0436\u043d\u043e \u0441\u0434\u0435\u043b\u0430\u0442\u044c \u043a\u0440\u043e\u0432\u043b\u044e. \u0411\u043e\u043b\u044c\u0448\u043e\u0435 \u0441\u043f\u0430\u0441\u0438\u0431\u043e!\n\n(\u041e\u0440\u0438\u0433\u0438\u043d\u0430\u043b)\nGreat experience with them did a great job exactly what I was told and even did more  like cleaning the guttering and no mess to be found around the job site. They were there and got the job done quicker than I thought it would be. Great people to work with and very honest which,is hard to find these days. Will be using them again when I need roofing done.  Thank You So much!"}, {"rating": 5, "text": "(\u041f\u0435\u0440\u0435\u0432\u0435\u0434\u0435\u043d\u043e Google) \u0412\u043e \u0432\u0440\u0435\u043c\u044f \u043f\u0440\u043e\u0433\u0443\u043b\u043a\u0438 \u044f \u043d\u0430\u0431\u043b\u044e\u0434\u0430\u043b \u0437\u0430 \u0440\u0430\u0431\u043e\u0442\u043e\u0439 JB Roofing. \u042f \u043f\u043e\u043d\u044f\u043b, \u043a\u0430\u043a \u043a\u0440\u0443\u0442\u043e \u0432\u044b\u0433\u043b\u044f\u0434\u0435\u043b \u0434\u043e\u043c, \u0438 \u043f\u043e\u043d\u044f\u043b, \u0447\u0442\u043e \u0445\u043e\u0447\u0443, \u0447\u0442\u043e\u0431\u044b \u044d\u0442\u0430 \u043a\u043e\u043c\u043f\u0430\u043d\u0438\u044f \u0443\u0441\u0442\u0430\u043d\u043e\u0432\u0438\u043b\u0430 \u043c\u043e\u044e \u043d\u043e\u0432\u0443\u044e \u043a\u0440\u044b\u0448\u0443 \u043d\u0430 \u043c\u043e\u0435\u043c \u0434\u043e\u043c\u0435.\n\u041f\u043e\u0441\u043b\u0435 \u043f\u0435\u0440\u0432\u043e\u0433\u043e \u0442\u0435\u043b\u0435\u0444\u043e\u043d\u043d\u043e\u0433\u043e \u0437\u0432\u043e\u043d\u043a\u0430 \u0438 \u043f\u0435\u0440\u0432\u043e\u043d\u0430\u0447\u0430\u043b\u044c\u043d\u043e\u0439 \u043e\u0446\u0435\u043d\u043a\u0438 \u0443\u0441\u0442\u0430\u043d\u043e\u0432\u043a\u0430 \u043d\u043e\u0432\u043e\u0439 \u043a\u0440\u044b\u0448\u0438 \u043f\u0440\u043e\u0438\u0437\u0432\u0435\u043b\u0430 \u043d\u0430 \u043c\u0435\u043d\u044f \u0431\u043e\u043b\u044c\u0448\u043e\u0435 \u0432\u043f\u0435\u0447\u0430\u0442\u043b\u0435\u043d\u0438\u0435. \u0414\u0436\u0430\u0440\u0435\u0434 \u043e\u0447\u0435\u043d\u044c \u043f\u043e\u0434\u0440\u043e\u0431\u043d\u043e \u0438 \u0438\u043d\u0444\u043e\u0440\u043c\u0430\u0442\u0438\u0432\u043d\u043e \u0440\u0430\u0441\u0441\u043a\u0430\u0437\u0430\u043b \u043c\u043d\u0435 \u043e \u043f\u0440\u043e\u0446\u0435\u0434\u0443\u0440\u0435, \u0442\u0430\u043a \u0447\u0442\u043e \u044f \u043c\u043e\u0433\u043b\u0430 \u043f\u0440\u0438\u043d\u044f\u0442\u044c \u0440\u0435\u0448\u0435\u043d\u0438\u0435 \u0431\u0435\u0437 \u0434\u0430\u0432\u043b\u0435\u043d\u0438\u044f. \u041f\u0440\u0438 \u0437\u0430\u043a\u0430\u0437\u0435 \u043a\u0440\u043e\u0432\u0435\u043b\u044c\u043d\u044b\u0445 \u043c\u0430\u0442\u0435\u0440\u0438\u0430\u043b\u043e\u0432 \u0414\u0436\u0430\u0440\u0435\u0434 \u043f\u043e\u0434\u0434\u0435\u0440\u0436\u0430\u043b \u043c\u043e\u0439 \u0432\u044b\u0431\u043e\u0440 \u0446\u0432\u0435\u0442\u0430 \u0438 \u0443\u043a\u0430\u0437\u0430\u043b \u0441\u0440\u043e\u043a\u0438 \u043f\u043e\u0441\u0442\u0430\u0432\u043a\u0438 \u043c\u0430\u0442\u0435\u0440\u0438\u0430\u043b\u043e\u0432 \u0438 \u0441\u0440\u043e\u043a\u0438 \u0443\u0441\u0442\u0430\u043d\u043e\u0432\u043a\u0438.\n\u041f\u0440\u0438 \u0443\u0441\u0442\u0430\u043d\u043e\u0432\u043a\u0435 \u043a\u0440\u044b\u0448\u0438 \u0414\u0436\u0430\u0440\u0435\u0434 \u0438 \u0422\u043e\u043c\u0430\u0441 \u0432\u0441\u0435\u0433\u0434\u0430 \u0431\u044b\u043b\u0438 \u043f\u0440\u043e\u0444\u0435\u0441\u0441\u0438\u043e\u043d\u0430\u043b\u044c\u043d\u044b, \u0432\u0441\u0435\u0433\u0434\u0430 \u043f\u0443\u043d\u043a\u0442\u0443\u0430\u043b\u044c\u043d\u044b, \u043f\u043e\u043b\u043d\u043e\u0441\u0442\u044c\u044e \u043f\u043e\u0441\u0432\u044f\u0442\u0438\u043b\u0438 \u0441\u0435\u0431\u044f \u0445\u043e\u0440\u043e\u0448\u043e \u0432\u044b\u043f\u043e\u043b\u043d\u0435\u043d\u043d\u043e\u0439 \u0440\u0430\u0431\u043e\u0442\u0435, \u0443\u0432\u0430\u0436\u0430\u043b\u0438 \u043c\u043e\u0438 \u043f\u0440\u043e\u0431\u043b\u0435\u043c\u044b \u0438 \u0432\u043e\u043f\u0440\u043e\u0441\u044b, \u0431\u044b\u043b\u0438 \u043e\u0447\u0435\u043d\u044c \u0432\u0435\u0436\u043b\u0438\u0432\u044b \u0438 \u043e\u0431\u0449\u0438\u0442\u0435\u043b\u044c\u043d\u044b \u0438 \u0441\u0442\u0440\u0435\u043c\u0438\u043b\u0438\u0441\u044c \u043a \u0441\u043e\u0432\u0435\u0440\u0448\u0435\u043d\u0441\u0442\u0432\u0443 \u043e\u0442 \u0441\u0430\u043c\u044b\u0445 \u0437\u0430\u043c\u0435\u0442\u043d\u044b\u0445 \u0434\u0435\u0442\u0430\u043b\u0435\u0439 \u0434\u043e \u043c\u0435\u043b\u044c\u0447\u0430\u0439\u0448\u0438\u0445 \u043d\u0435\u0432\u0438\u0434\u0438\u043c\u044b\u0445 \u0434\u0435\u0442\u0430\u043b\u0435\u0439. \u041e\u0431\u0430 \u043c\u0443\u0436\u0447\u0438\u043d\u044b \u043e\u0447\u0435\u043d\u044c \u0445\u043e\u0440\u043e\u0448\u043e \u043e\u0441\u0432\u0435\u0434\u043e\u043c\u043b\u0435\u043d\u044b \u0432\u043e \u0432\u0441\u0435\u0445 \u0430\u0441\u043f\u0435\u043a\u0442\u0430\u0445 \u043a\u0440\u043e\u0432\u0435\u043b\u044c\u043d\u044b\u0445 \u0440\u0430\u0431\u043e\u0442.\n\u041f\u043e\u0441\u043b\u0435 \u0443\u0441\u0442\u0430\u043d\u043e\u0432\u043a\u0438 \u043a\u0440\u044b\u0448\u0438 \u0442\u0435\u0440\u0440\u0438\u0442\u043e\u0440\u0438\u044f \u0432\u043e\u043a\u0440\u0443\u0433 \u043c\u043e\u0435\u0433\u043e \u0434\u043e\u043c\u0430 \u0431\u044b\u043b\u0430 \u043f\u043e\u043b\u043d\u043e\u0441\u0442\u044c\u044e \u043e\u0447\u0438\u0449\u0435\u043d\u0430. \u041a\u0430\u043a \u043c\u043d\u0435 \u0441\u043a\u0430\u0437\u0430\u043b\u0438, \u043e\u043d\u0438 \u0443\u0445\u043e\u0434\u044f\u0442 \u0441 \u0443\u0447\u0430\u0441\u0442\u043a\u0430, \u043a\u0430\u043a \u0431\u0443\u0434\u0442\u043e \u0438 \u043d\u0435 \u0431\u044b\u043b\u0438 \u043d\u0430 \u0442\u0435\u0440\u0440\u0438\u0442\u043e\u0440\u0438\u0438. \u042d\u0442\u043e \u0434\u0435\u043b\u0430\u043b\u043e\u0441\u044c \u043a\u0430\u0436\u0434\u044b\u0439 \u0434\u0435\u043d\u044c. \u042f \u0431\u044b\u043b \u0442\u0430\u043a \u0431\u043b\u0430\u0433\u043e\u0434\u0430\u0440\u0435\u043d \u0437\u0430 \u0438\u0445 \u0447\u0435\u0441\u0442\u043d\u043e\u0441\u0442\u044c. \u0420\u0430\u043d\u044c\u0448\u0435 \u0443 \u043c\u0435\u043d\u044f \u0431\u044b\u043b\u0438 \u043f\u043e\u0434\u0440\u044f\u0434\u0447\u0438\u043a\u0438, \u0438 \u0443\u0431\u043e\u0440\u043a\u0430 \u043d\u0435 \u043f\u0440\u043e\u0438\u0437\u0432\u043e\u0434\u0438\u043b\u0430\u0441\u044c \u0435\u0436\u0435\u0434\u043d\u0435\u0432\u043d\u043e.\n\u041f\u043e\u0434\u0432\u043e\u0434\u044f \u0438\u0442\u043e\u0433, \u044f \u0431\u044b \u043f\u043e\u0440\u0435\u043a\u043e\u043c\u0435\u043d\u0434\u043e\u0432\u0430\u043b JB Roofing, \u043f\u043e\u0442\u043e\u043c\u0443 \u0447\u0442\u043e \u043e\u0431\u0430 \u0440\u0430\u0431\u043e\u0442\u0430\u044e\u0442 \u043d\u0430 \u0441\u043e\u0432\u0435\u0440\u0448\u0435\u043d\u0441\u0442\u0432\u043e\u0432\u0430\u043d\u0438\u0435 \u0438 \u043d\u0430 \u0443\u0434\u043e\u0432\u043b\u0435\u0442\u0432\u043e\u0440\u0435\u043d\u0438\u0435 \u043f\u043e\u0442\u0440\u0435\u0431\u043d\u043e\u0441\u0442\u0435\u0439 \u043a\u043b\u0438\u0435\u043d\u0442\u043e\u0432. JB Roofing \u0432 \u0441\u043e\u0432\u043e\u043a\u0443\u043f\u043d\u043e\u0441\u0442\u0438 \u0441\u043f\u0440\u0430\u0432\u0435\u0434\u043b\u0438\u0432\u0430 \u0438 \u0447\u0435\u0441\u0442\u043d\u0430, \u0432\u0441\u0435\u0433\u0434\u0430 \u043f\u0443\u043d\u043a\u0442\u0443\u0430\u043b\u044c\u043d\u0430, \u043e\u0431\u043b\u0430\u0434\u0430\u0435\u0442 \u043e\u0442\u043b\u0438\u0447\u043d\u043e\u0439 \u0440\u0430\u0431\u043e\u0447\u0435\u0439 \u044d\u0442\u0438\u043a\u043e\u0439 \u0438 \u0444\u0438\u043b\u043e\u0441\u043e\u0444\u0438\u0435\u0439 \u0440\u0430\u0431\u043e\u0442\u044b, \u043e\u0447\u0435\u043d\u044c \u043f\u0440\u043e\u0444\u0435\u0441\u0441\u0438\u043e\u043d\u0430\u043b\u044c\u043d\u0430 \u0441 \u043a\u043b\u0438\u0435\u043d\u0442\u0430\u043c\u0438, \u043f\u043e\u0441\u0442\u043e\u044f\u043d\u043d\u043e \u0438\u043d\u0444\u043e\u0440\u043c\u0430\u0442\u0438\u0432\u043d\u0430 \u0438 \u043f\u043e\u0434\u0434\u0435\u0440\u0436\u0438\u0432\u0430\u0435\u0442 \u0432\u044b\u0441\u043e\u043a\u0438\u0435 \u0441\u0442\u0430\u043d\u0434\u0430\u0440\u0442\u044b \u0440\u0430\u0431\u043e\u0442\u044b \u0434\u043e \u0437\u0430\u0432\u0435\u0440\u0448\u0435\u043d\u0438\u044f \u0440\u0430\u0431\u043e\u0442\u044b. \u042f \u043e\u0447\u0435\u043d\u044c \u0446\u0435\u043d\u044e \u043e\u0431\u043e\u0438\u0445 \u044d\u0442\u0438\u0445 \u043b\u044e\u0434\u0435\u0439 \u0438 \u043f\u0440\u0435\u043a\u0440\u0430\u0441\u043d\u0443\u044e \u0443\u0441\u0442\u0430\u043d\u043e\u0432\u043a\u0443 \u043c\u043e\u0435\u0439 \u043d\u043e\u0432\u043e\u0439 \u043a\u0440\u044b\u0448\u0438.\n\u0421\u043f\u0430\u0441\u0438\u0431\u043e \u0432\u0430\u043c \u043e\u0431\u043e\u0438\u043c, \u043b\u044e\u0431\u0435\u0437\u043d\u043e, \u0413. \u0425\u043e\u043b\u043b\u0438.\n\n(\u041e\u0440\u0438\u0433\u0438\u043d\u0430\u043b)\nI had observed the work of JB Roofing while walking. I realized how awesome the house looked and knew that I wanted this company to install my new roof on my house.\nFrom the first phone call and initial assessment, the new roof installation had been a great experience. Jared was very detailed and informative about the procedure so that I could make my decision without pressure. With the ordering of roofing materials, Jared supported my color selection and provided delivery dates of materials and installation dates.\nWith the roof installation, Jared and Thomas were constantly professional, always punctual, completely dedicated to a job well done, respected my concerns and questions, very polite and socialable, and strived for perfection from the most visible details to the smallest unseen details. Both men are very knowledgeable with all aspects of roofing.\nAfter roof installation, the grounds around my house were cleaned completely. As I was told, they leave the worksite, as if, they had never been on the grounds. This was done everyday. I was so appreciative of their honesty. I have had contractors before doing jobs and cleanups were not performed daily.\nTo summarize, I would recommend JB Roofing because both men work for perfection and toward customer's satisfaction. JB Roofing, collectively, is fair and honest, always punctual, possesses great work ethnics and work philosophy, very professional with customers, routinely informative, and maintains high job standards until the completion of the job. I greatly appreciate both of these men and the beautiful installation of my new roof.\nThank you both, kindly, G. Holley"}, {"rating": 5, "text": "(\u041f\u0435\u0440\u0435\u0432\u0435\u0434\u0435\u043d\u043e Google) \u0423 \u043d\u0430\u0441 \u0435\u0441\u0442\u044c \u0431\u043e\u043b\u044c\u0448\u043e\u0439 \u043e\u043f\u044b\u0442 \u0440\u0430\u0431\u043e\u0442\u044b \u0441 \u0448\u0430\u0440\u043e\u0432\u043e\u0439 \u043a\u0440\u043e\u0432\u043b\u0435\u0439 Jimmy. \u0414\u0436\u0430\u0440\u0435\u0434 \u043f\u0440\u0438\u0448\u0435\u043b \u0443\u0441\u0442\u0430\u043d\u043e\u0432\u0438\u0442\u044c \u043a\u0440\u044b\u0448\u0443 \u043d\u0430\u0448\u0435\u0433\u043e \u0433\u0430\u0440\u0430\u0436\u0430. \u0420\u0430\u0431\u043e\u0442\u0430 \u0438 \u044d\u043a\u0438\u043f\u0430\u0436 \u0431\u044b\u043b\u0438 \u043e\u0447\u0435\u043d\u044c \u043f\u0440\u043e\u0444\u0435\u0441\u0441\u0438\u043e\u043d\u0430\u043b\u044c\u043d\u044b\u043c\u0438. \u0414\u0436\u0430\u0440\u0435\u0434 \u0432\u0435\u0440\u043d\u0443\u043b\u0441\u044f, \u0447\u0442\u043e\u0431\u044b \u0437\u0430\u043d\u044f\u0442\u044c\u0441\u044f \u043a\u0440\u043e\u0432\u043b\u0435\u0439 \u043d\u0430\u0448\u0435\u0433\u043e \u0434\u043e\u043c\u0430, \u0438 \u043e\u043d \u0441\u043c\u043e\u0433 \u0441\u0434\u0435\u043b\u0430\u0442\u044c \u0434\u043b\u044f \u043d\u0430\u0441 \u043d\u0435\u0431\u043e\u043b\u044c\u0448\u043e\u0439 \u0440\u0435\u043c\u043e\u043d\u0442 \u0438 \u043f\u043e\u0440\u0430\u0431\u043e\u0442\u0430\u0442\u044c. \u041e\u043d \u0431\u044b\u043b \u043e\u0447\u0435\u043d\u044c \u043f\u0440\u043e\u0444\u0435\u0441\u0441\u0438\u043e\u043d\u0430\u043b\u044c\u043d\u044b\u043c \u0438 \u0434\u0440\u0443\u0436\u0435\u043b\u044e\u0431\u043d\u044b\u043c. \u041e\u043d \u0441\u0434\u0435\u043b\u0430\u043b \u0431\u043e\u043b\u044c\u0448\u0443\u044e \u0440\u0430\u0431\u043e\u0442\u0443!\n\n(\u041e\u0440\u0438\u0433\u0438\u043d\u0430\u043b)\nWe have had a great experience with Jimmy ball roofing. Jared came out to install our garage roof. The work and the crew were very professional. Jared came back to address our house roof and was able to do some minor repairs and work for us. He was very professional and very friendly. He did a great job!"}, {"rating": 1, "text": "(\u041f\u0435\u0440\u0435\u0432\u0435\u0434\u0435\u043d\u043e Google) \u0418\u0441\u043f\u043e\u043b\u044c\u0437\u043e\u0432\u0430\u0442\u044c \u0438\u0437\u0433\u043e\u0442\u043e\u0432\u043b\u0435\u043d\u043d\u0443\u044e \u0431\u0440\u0430\u043a\u043e\u0432\u0430\u043d\u043d\u0443\u044e \u0447\u0435\u0440\u0435\u043f\u0438\u0446\u0443 \u0438 \u043f\u0440\u043e\u0441\u043e\u0447\u0438\u0442\u044c\u0441\u044f \u0432 \u0442\u0435\u0447\u0435\u043d\u0438\u0435 3 \u043c\u0435\u0441\u044f\u0446\u0435\u0432, \u0441\u0434\u0443\u0442\u044c \u0432\u0435\u0442\u0435\u0440 \u0441 \u043a\u0440\u044b\u0448\u0438 \u0438 \u0440\u0430\u0437\u0432\u0430\u043b\u0438\u0442\u044c\u0441\u044f. \u0415\u0441\u043b\u0438 \u0431\u044b \u0441\u0435\u0433\u043e\u0434\u043d\u044f \u0434\u0440\u0443\u0433\u043e\u0439 \u043a\u0440\u043e\u0432\u0435\u043b\u044c\u0449\u0438\u043a \u043f\u043e\u0447\u0438\u043d\u0438\u043b \u043c\u043e\u044e \u043a\u0440\u044b\u0448\u0443, \u0441\u0442\u043e\u0438\u043c\u043e\u0441\u0442\u044c \u043a\u043e\u0442\u043e\u0440\u043e\u0439 500 \u0434\u043e\u043b\u043b\u0430\u0440\u043e\u0432, \u0437\u0430\u044f\u0432\u0438\u043b, \u0447\u0442\u043e \u043e\u043d \u043d\u0435 \u043f\u043e\u043b\u043e\u0436\u0438\u043b \u0434\u043e\u0441\u0442\u0430\u0442\u043e\u0447\u043d\u043e\u0435 \u043a\u043e\u043b\u0438\u0447\u0435\u0441\u0442\u0432\u043e \u0433\u0432\u043e\u0437\u0434\u0435\u0439 \u0432 \u0447\u0435\u0440\u0435\u043f\u0438\u0446\u0443, \u043f\u0440\u0438\u0448\u043b\u043e\u0441\u044c \u0437\u0430\u043c\u0435\u043d\u0438\u0442\u044c \u043f\u043b\u0438\u0442\u0443 \u0438\u0437-\u0437\u0430 \u0443\u0442\u0435\u0447\u0435\u043a, \u0447\u0435\u0440\u0435\u043f\u0438\u0446\u0430 \u043e\u0442\u0434\u0435\u043b\u0438\u043b\u0430\u0441\u044c \u043e\u0442 \u0433\u0432\u043e\u0437\u0434\u0435\u0439 \u0438\u0437-\u0437\u0430 \u0434\u0435\u0444\u0435\u043a\u0442\u043d\u043e\u0439 \u0447\u0435\u0440\u0435\u043f\u0438\u0446\u044b, \u0432\u0441\u0435 \u0443\u043f\u043b\u043e\u0442\u043d\u0435\u043d\u0438\u044f \u043d\u0430 \u0447\u0435\u0440\u0435\u043f\u0438\u0446\u0435 \u0431\u044b\u043b\u0438 \u0441\u043c\u044b\u0442\u044b \u0432 \u0442\u0435\u0447\u0435\u043d\u0438\u0435 2 \u043b\u0435\u0442 \u0422\u0435\u043f\u0435\u0440\u044c \u043f\u0440\u0438\u0434\u0435\u0442\u0441\u044f \u0437\u0430\u043c\u0435\u043d\u0438\u0442\u044c \u043a\u0440\u043e\u0432\u043b\u044e \u0438 \u0447\u0435\u0440\u0435\u043f\u0438\u0446\u0443 \u0432 \u0442\u0435\u0447\u0435\u043d\u0438\u0435 7 \u043b\u0435\u0442 \u0438 \u043e\u043f\u043b\u0430\u0442\u0438\u0442\u044c 30-\u043b\u0435\u0442\u043d\u044e\u044e \u0430\u0440\u0445\u0438\u0442\u0435\u043a\u0442\u0443\u0440\u043d\u0443\u044e \u0447\u0435\u0440\u0435\u043f\u0438\u0446\u0443.\n\n(\u041e\u0440\u0438\u0433\u0438\u043d\u0430\u043b)\nUse manufactured defected shingles and leaked within 3 months, wind blowed shingles off roof and came apart. Had another roofer fix my roof today which coast $500, stated that he didn't put enough nails in shingles, have to replace plyboard due to leaks, shingles separated from nails due to defected shingles, all sealing on shingles had washed away within 2 years, now have to replace roof and shingles within 7 years and paid for 30 year architectural shingles."}, {"rating": 4, "text": "(\u041f\u0435\u0440\u0435\u0432\u0435\u0434\u0435\u043d\u043e Google) \u0412\u0441\u0435 \u0435\u0449\u0435 \u0432 \u043f\u0440\u043e\u0446\u0435\u0441\u0441\u0435 \u0437\u0430\u0432\u0435\u0440\u0448\u0435\u043d\u0438\u044f \u0440\u0430\u0431\u043e\u0442\u044b, \u043f\u043e\u043a\u0430 \u044f \u043f\u0435\u0447\u0430\u0442\u0430\u044e \u044d\u0442\u043e. \u042f \u043e\u0431\u043d\u043e\u0432\u043b\u044e, \u043a\u043e\u0433\u0434\u0430 \u043f\u0440\u0438\u0434\u0435\u0442 \u0432\u0440\u0435\u043c\u044f \u0441\u0434\u0435\u043b\u0430\u0442\u044c \u044d\u0442\u043e \u0438 \u0437\u0430\u0432\u0435\u0440\u0448\u0438\u0442\u044c.\n\n(\u041e\u0440\u0438\u0433\u0438\u043d\u0430\u043b)\nStill in the process of getting the work completed as I am typing this. I will update when the time comes to do so and completed."}, {"rating": 5, "text": "(\u041f\u0435\u0440\u0435\u0432\u0435\u0434\u0435\u043d\u043e Google) \u041e\u0447\u0435\u043d\u044c \u043f\u0440\u043e\u0444\u0435\u0441\u0441\u0438\u043e\u043d\u0430\u043b\u044c\u043d\u044b\u0439 \u0438 \u043e\u0442\u043b\u0438\u0447\u043d\u044b\u0439 \u0441\u0435\u0440\u0432\u0438\u0441, \u0441\u043f\u0430\u0441\u0438\u0431\u043e Jimmy Ball Roofing\n\n(\u041e\u0440\u0438\u0433\u0438\u043d\u0430\u043b)\nVery professional and excellent service thanks jimmy ball roofing"}, {"rating": 1, "text": "(\u041f\u0435\u0440\u0435\u0432\u0435\u0434\u0435\u043d\u043e Google) \u041d\u0435 \u043e\u0442\u0432\u0435\u0447\u0430\u0435\u0442 \u043d\u0430 \u0442\u0435\u043b\u0435\u0444\u043e\u043d\u043d\u044b\u0435 \u0437\u0432\u043e\u043d\u043a\u0438, \u043d\u0435 \u0434\u043e\u043b\u0436\u0435\u043d \u0431\u044b\u0442\u044c \u0437\u0430\u0438\u043d\u0442\u0435\u0440\u0435\u0441\u043e\u0432\u0430\u043d \u0432 \u0432\u0435\u0434\u0435\u043d\u0438\u0438 \u0431\u0438\u0437\u043d\u0435\u0441\u0430\n\n(\u041e\u0440\u0438\u0433\u0438\u043d\u0430\u043b)\nWill not return any phone calls must not be interested in doing any business"}], "photos": ["https://lh5.googleusercontent.com/p/AF1QipOzWEVI6au3nfXNjpO5ravJXEk98z1R7Scrr7YT", "https://lh5.googleusercontent.com/p/AF1QipNWTkOXy11ddCJp-_30ZL5Usosav8rt60M46mle", "https://lh5.googleusercontent.com/p/AF1QipNwHlBWiVJh3NKIOfKjb6NJdGAauoiZuV91QGrJ", "https://lh5.googleusercontent.com/p/AF1QipNz9tkp7RuPQ84QLWfSliKWBoW3Rzyg4HvXf6E6", "https://lh5.googleusercontent.com/p/AF1QipO4VwdIRutFM3mKqbjHp9gKeDr42tsv1GnwNA6j", "https://lh5.googleusercontent.com/p/AF1QipO3qpcK-kF72bT1xXfnAsW_6N6_SbNa3X0RWcBi", "https://lh5.googleusercontent.com/p/AF1QipPowSGaOr-KA_3FM3F1GaMUrLClcC1dr0E1Amat", "https://lh5.googleusercontent.com/p/AF1QipMEkX5tI1PdFDc86wLiqQFMuiL2lh66ICTozUze"]}